w3u/__init__.py
w3utils/__init__.py
w3utils/w3utils.py
w3u-0.17.0.dist-info/METADATA
w3u-0.17.0.dist-info/WHEEL
w3u-0.17.0.dist-info/top_level.txt
w3u-0.17.0.dist-info/RECORD
