Metadata-Version: 2.1
Name: w3u
Version: 0.17.0
Summary: My short description for my project.
Home-page: https://github.com/thegismar/w3u
Author: thegismar
Author-email: thegismar@thegismar.com
License: MIT
Platform: UNKNOWN
Classifier: License :: OSI Approved :: MIT License
Classifier: Programming Language :: Python
Classifier: Programming Language :: Python :: 3
Classifier: Programming Language :: Python :: 3.6
Classifier: Programming Language :: Python :: Implementation :: CPython
Classifier: Programming Language :: Python :: Implementation :: PyPy
Requires-Python: >=3.6.0
Requires-Dist: pandas
Requires-Dist: requests
